python_wakatime/__init__.py
python_wakatime/_metainfo.py
python_wakatime/_version.py
python_wakatime/ipython.py
python_wakatime/ptpython.py
python_wakatime/py.typed
python_wakatime/python.py
python_wakatime/utils.py
python_wakatime-0.0.3.dist-info/LICENSE
python_wakatime-0.0.3.dist-info/METADATA
python_wakatime-0.0.3.dist-info/WHEEL
python_wakatime-0.0.3.dist-info/top_level.txt
python_wakatime-0.0.3.dist-info/RECORD
